aica_challenge_1/__init__.py
aica_challenge_1/agent_template._zip
aica_challenge_1/challenge.py
aica_challenge_1/cmd_interface.py
aica_challenge_1/delay_defender.py
aica_challenge_1/execution_manager.py
aica_challenge_1/execution_structures.py
aica_challenge_1/launcher.py
aica_challenge_1/model.py
aica_challenge_1/package_manager.py
aica_challenge_1/scenario_manager.py
aica_challenge_1-1.5.0.dist-info/entry_points.txt
aica_challenge_1-1.5.0.dist-info/METADATA
aica_challenge_1-1.5.0.dist-info/WHEEL
aica_challenge_1-1.5.0.dist-info/RECORD
