Metadata-Version: 2.3
Name: aica-challenge-1
Version: 1.5.0
Summary: 
Author: Martin Drasar
Author-email: drasar@ics.muni.cz
Requires-Python: ==3.12.*
Classifier: Programming Language :: Python :: 3
Classifier: Programming Language :: Python :: 3.12
Requires-Dist: click (>=8.2.1,<9.0.0)
Requires-Dist: curses-menu (>=0.9.0,<0.10.0)
Requires-Dist: cyst-core (>=0.6.5)
Requires-Dist: psutil (>=7.0.0,<8.0.0)
Requires-Dist: python-cli-menu (>=1.8.1,<2.0.0)
Requires-Dist: requests (>=2.32.4,<3.0.0)
Requires-Dist: sqlalchemy (>=2.0.41,<3.0.0)
